tupload/__init__.py
tupload/tupload.py
tupload-0.1.4.dist-info/LICENSE
tupload-0.1.4.dist-info/METADATA
tupload-0.1.4.dist-info/WHEEL
tupload-0.1.4.dist-info/entry_points.txt
tupload-0.1.4.dist-info/top_level.txt
tupload-0.1.4.dist-info/RECORD
