Metadata-Version: 2.1
Name: tupload
Version: 0.1.4
Summary: Telegram bot to fetch files from the client
Home-page: https://www.github.com/ritiek/tupload
Author: Ritiek Malhotra
Author-email: ritiekmalhotra123@gmail.com
License: MIT
Download-URL: https://github.com/ritiek/tupload/archive/v0.1.4.tar.gz
Keywords: telegram,bot,upload,download,files
Platform: UNKNOWN
Requires-Dist: pyperclip
Requires-Dist: telepot
